{"stats":{"minecraft:picked_up":{"minecraft:fishing_rod":1,"minecraft:wolf_armor":1,"minecraft:porkchop":311,"minecraft:apple":13,"minecraft:oak_button":4},"minecraft:used":{"minecraft:moss_block":11,"minecraft:netherite_sword":28,"minecraft:iron_bars":2,"minecraft:black_concrete":214,"minecraft:apple":10,"minecraft:orange_concrete":33,"minecraft:command_block":76,"minecraft:red_concrete":81,"minecraft:birch_planks":29,"minecraft:pig_spawn_egg":174,"minecraft:grass_block":216,"minecraft:barrier":187,"minecraft:redstone":4,"minecraft:oak_button":26,"minecraft:oak_planks":2,"minecraft:oak_sign":7,"minecraft:brown_concrete":27,"minecraft:stone":4,"minecraft:glow_ink_sac":2,"minecraft:oak_leaves":11,"minecraft:pink_concrete":29,"minecraft:purple_concrete":26,"minecraft:golden_apple":3,"minecraft:fishing_rod":76,"minecraft:repeater":52,"minecraft:dirt":12,"minecraft:lime_concrete":29,"minecraft:comparator":1,"minecraft:white_carpet":2,"minecraft:light_blue_concrete":29,"minecraft:yellow_concrete":52,"minecraft:repeating_command_block":47,"minecraft:white_concrete":121,"minecraft:spruce_log":2},"minecraft:custom":{"minecraft:time_since_rest":240613,"minecraft:sprint_one_cm":188916,"minecraft:walk_one_cm":203373,"minecraft:damage_taken":634,"minecraft:mob_kills":45,"minecraft:damage_dealt":2015,"minecraft:swim_one_cm":104641,"minecraft:fly_one_cm":4253659,"minecraft:open_chest":1,"minecraft:crouch_one_cm":28883,"minecraft:open_shulker_box":97,"minecraft:play_time":270696,"minecraft:deaths":1,"minecraft:walk_under_water_one_cm":40689,"minecraft:sneak_time":14537,"minecraft:boat_one_cm":1927,"minecraft:jump":2287,"minecraft:leave_game":13,"minecraft:time_since_death":240593,"minecraft:walk_on_water_one_cm":16981,"minecraft:total_world_time":270696,"minecraft:climb_one_cm":24789,"minecraft:fall_one_cm":13019},"minecraft:killed":{"minecraft:pig":17}},"DataVersion":3839}