{"stats":{"minecraft:used":{"minecraft:bedrock":1,"minecraft:sand":5,"minecraft:firework_rocket":126,"minecraft:crimson_fence":2,"minecraft:grass_block":2,"minecraft:barrier":1,"minecraft:elytra":1,"minecraft:minecart":3,"minecraft:birch_boat":2,"minecraft:stone":4},"minecraft:custom":{"minecraft:time_since_rest":47470,"minecraft:open_chest":6,"minecraft:crouch_one_cm":1210,"minecraft:play_time":47470,"minecraft:sprint_one_cm":55017,"minecraft:open_enderchest":1,"minecraft:damage_taken":10,"minecraft:walk_one_cm":32951,"minecraft:sneak_time":2508,"minecraft:walk_under_water_one_cm":9675,"minecraft:interact_with_anvil":1,"minecraft:boat_one_cm":64452,"minecraft:aviate_one_cm":617865,"minecraft:jump":526,"minecraft:leave_game":1,"minecraft:time_since_death":47470,"minecraft:walk_on_water_one_cm":16610,"minecraft:total_world_time":47470,"minecraft:climb_one_cm":5915,"minecraft:swim_one_cm":14656,"minecraft:interact_with_crafting_table":1,"minecraft:fall_one_cm":420,"minecraft:fly_one_cm":1790620,"minecraft:inspect_dispenser":1},"minecraft:picked_up":{"minecraft:birch_boat":2,"minecraft:leather_helmet":1}},"DataVersion":3839}